setup.py
django_lazycache.egg-info/PKG-INFO
django_lazycache.egg-info/SOURCES.txt
django_lazycache.egg-info/dependency_links.txt
django_lazycache.egg-info/requires.txt
django_lazycache.egg-info/top_level.txt
lazycache/__init__.py
lazycache/lists.py
lazycache/tests.py
lazymodel/__init__.py
lazymodel/backend.py
lazymodel/models.py
lazymodel/tests.py
lazymodel/utils.py