Metadata-Version: 1.0
Name: django-lazycache
Version: 0.0.1
Summary: Caching for Django models.
Home-page: https://github.com/apn-online/django-lazycache
Author: Raymond Butcher
Author-email: randomy@gmail.com
License: MIT
Platform: UNKNOWN
